[
  {
    "id": "item_security_card",
    "name": "安保卡",
    "type": "KEY",
    "description": "一张印有千禧塔logo的磁卡，边缘略微磨损。背面贴着一张便利贴，上面写着'管理员权限——请勿外借'。"
  },
  {
    "id": "item_server_key",
    "name": "服务器机房钥匙",
    "type": "KEY",
    "description": "一把厚重的金属钥匙，手柄上刻着'5F-SR-07'。钥匙表面覆盖着一层奇怪的冷凝水，摸上去异常冰冷。"
  },
  {
    "id": "item_lab_pass",
    "name": "实验室通行证",
    "type": "KEY",
    "description": "一张全息防伪通行证，上面写着'9F中央实验室——仅限授权人员'。通行证在灯光下折射出不正常的紫色光晕。"
  },
  {
    "id": "item_data_shard_1",
    "name": "数据碎片 I",
    "type": "QUEST",
    "description": "一块半透明的晶体，内部有微弱的光流转。凑近看时，能隐约听到模糊的数据低语——似乎是某位研究员的实验日志片段。"
  },
  {
    "id": "item_data_shard_2",
    "name": "数据碎片 II",
    "type": "QUEST",
    "description": "比第一块颜色更深的碎片，光芒如脉搏般跳动。触碰时指尖产生静电刺痛感，脑海中闪过一组模糊的服务器阵列图像。"
  },
  {
    "id": "item_data_shard_3",
    "name": "数据碎片 III",
    "type": "QUEST",
    "description": "最大的碎片，内部光芒已稳定如心跳。握在手中能清晰地感受到一种不属于人类的思维节律，仿佛它在等待被拼接到某个更大的整体中。"
  },
  {
    "id": "item_sedative",
    "name": "镇定剂",
    "type": "CONSUMABLE",
    "description": "千年科学学院医务室的标准配给。标签上写着'适用于轻度认知混乱及急性焦虑发作'。柚子把它塞进你手里时，手微微发抖。"
  },
  {
    "id": "item_coolant_injector",
    "name": "冷却剂注射器",
    "type": "CONSUMABLE",
    "description": "一支散发着淡淡蓝光的注射器，握在手中能感到一阵清凉。标签上的使用说明已被涂抹掉大半，只剩下'体温过低风险'几个字依然清晰。"
  },
  {
    "id": "item_signal_jammer",
    "name": "信号干扰器",
    "type": "EQUIPMENT",
    "description": "柚子改装的小型设备，能发出特定频率的电磁脉冲。她调试时曾不经意地说'它可以暂时屏蔽那些东西的……感知'，然后迅速转移了话题。"
  },
  {
    "id": "item_transceiver",
    "name": "旧式收发器",
    "type": "EQUIPMENT",
    "description": "一台略显老旧的无线通讯设备。屏幕上偶然会闪过一些不属于任何已知频段的信号波形——像是某种以电磁波为载体的古老语言。"
  },
  {
    "id": "item_pipe_sample",
    "name": "管道样本",
    "type": "MISC",
    "description": "从下水道管道壁上刮下的样本。装在密封试管中，样本表面生长着一种发出微弱荧光的苔藓状物质——在实验室外从未见过这种有机结构。"
  },
  {
    "id": "item_frequency_recording",
    "name": "频率录音",
    "type": "MISC",
    "description": "用旧式收发器录下的异常信号。回放时，扬声器传出一种深沉、缓慢的脉冲声。连续听超过30秒后，你会开始觉得那声音像是一种语言的片段。"
  },
  {
    "id": "item_guard_log",
    "name": "守卫日志",
    "type": "MISC",
    "description": "一本翻旧的日志本。前30页都是正常的巡逻记录，但从中段开始，字迹逐渐变得潦草、重复，最后几页写满了同一句话：'它在墙里面，它在墙里面，它在墙里面。'"
  },
  {
    "id": "item_student_note",
    "name": "学生笔记",
    "type": "MISC",
    "description": "一本学生的课堂笔记本。正常笔记只写了一半，后半本画满了令人不安的几何图案——一种由嵌套的同心圆和放射线组成的符号，似乎在试图描绘某种更高维度的结构。"
  },
  {
    "id": "item_seal_shard",
    "name": "封印碎片",
    "type": "MISC",
    "description": "一块刻着未知符号的石片，断口新鲜。那些刻痕似乎不是凿出来的——更像是被某种极端力量从内部震裂。石片表面在不接触任何热源的情况下持续散发着微热。"
  },
  {
    "id": "item_forbidden_tome",
    "name": "禁忌古籍",
    "type": "MISC",
    "description": "一本没有任何出版信息的古籍，封皮是一种无法辨认的皮革材质。书页间的文字不属于任何已知语言，但当你凝视那些符号超过片刻，它们会在你的视野中微微扭曲，仿佛试图重新排列成你能够理解的形式。"
  },
  {
    "id": "item_truth_crystal",
    "name": "真理水晶",
    "type": "MISC",
    "description": "一块完美切割的水晶棱柱。当你透过它看向任何物体时，你能看到那个物体的'反面'——不是镜像，而是一种无法用三维空间理解的结构。柚子不敢直视它超过三秒。"
  },
  {
    "id": "item_cable_analysis",
    "name": "缆线分析报告",
    "type": "MISC",
    "description": "一份标记为'最高机密'的技术报告，分析了千禧塔地下缆线的异常能量读数。报告的结论部分被墨迹完全覆盖，但在背面有一行手写的备注：'不是电缆——是神经。'"
  },
  {
    "id": "item_resonance_diagram",
    "name": "共鸣图谱",
    "type": "MISC",
    "description": "系统管理员绘制的服务器共鸣频率图。正常数据图表之外，有人用红笔在空白处画了一个巨大的、由纵横交错的线条组成的结构图——看起来像一座倒立的塔。"
  },
  {
    "id": "item_experiment_log",
    "name": "实验日志",
    "type": "MISC",
    "description": "实验体零号的连续观察记录。日志中记载了实验体的细胞在显微镜下表现出的异常行为：它们似乎在以一种有序的方式重组自己——试图拼写出某种符号。"
  }
]
